marshmallow_union/__init__.py
marshmallow_union-0.1.15.dist-info/AUTHORS.rst
marshmallow_union-0.1.15.dist-info/LICENSE
marshmallow_union-0.1.15.dist-info/METADATA
marshmallow_union-0.1.15.dist-info/WHEEL
marshmallow_union-0.1.15.dist-info/top_level.txt
marshmallow_union-0.1.15.dist-info/RECORD
